[
    {
        "op": "add",
        "path": "/channels/0/samples/0",
        "value": {
            "data": [
                2.3912465572357178
            ],
            "modifiers": [
                {
                    "data": null,
                    "name": "lumi",
                    "type": "lumi"
                },
                {
                    "data": [
                        0.3754387441395898
                    ],
                    "name": "staterror_CRtt_cuts",
                    "type": "staterror"
                },
                {
                    "data": {
                        "hi": 1.088,
                        "lo": 0.9369
                    },
                    "name": "SigRad",
                    "type": "normsys"
                },
                {
                    "data": null,
                    "name": "mu_SIG",
                    "type": "normfactor"
                },
                {
                    "data": {
                        "hi_data": [
                            2.3912465572357178
                        ],
                        "lo_data": [
                            2.3912465572357178
                        ]
                    },
                    "name": "EL_EFF_ChargeIDSel_TOTAL_1NPCOR_PLUS_UNCOR",
                    "type": "histosys"
                },
                {
                    "data": {
                        "hi_data": [
                            2.401728630065918
                        ],
                        "lo_data": [
                            2.3807644844055176
                        ]
                    },
                    "name": "EL_EFF_ID_TOTAL_1NPCOR_PLUS_UNCOR",
                    "type": "histosys"
                },
                {
                    "data": {
                        "hi_data": [
                            2.3942062854766846
                        ],
                        "lo_data": [
                            2.3882875442504883
                        ]
                    },
                    "name": "EL_EFF_Iso_TOTAL_1NPCOR_PLUS_UNCOR",
                    "type": "histosys"
                },
                {
                    "data": {
                        "hi_data": [
                            2.3928382396698
                        ],
                        "lo_data": [
                            2.389655351638794
                        ]
                    },
                    "name": "EL_EFF_Reco_TOTAL_1NPCOR_PLUS_UNCOR",
                    "type": "histosys"
                },
                {
                    "data": {
                        "hi_data": [
                            2.3912465572357178
                        ],
                        "lo_data": [
                            2.3912465572357178
                        ]
                    },
                    "name": "EL_EFF_TriggerEff_TOTAL_1NPCOR_PLUS_UNCOR",
                    "type": "histosys"
                },
                {
                    "data": {
                        "hi_data": [
                            2.3912465572357178
                        ],
                        "lo_data": [
                            2.3912465572357178
                        ]
                    },
                    "name": "EL_EFF_Trigger_TOTAL_1NPCOR_PLUS_UNCOR",
                    "type": "histosys"
                },
                {
                    "data": {
                        "hi_data": [
                            2.4655709266662598
                        ],
                        "lo_data": [
                            2.31701397895813
                        ]
                    },
                    "name": "FT_EFF_B_systematics",
                    "type": "histosys"
                },
                {
                    "data": {
                        "hi_data": [
                            2.41606068611145
                        ],
                        "lo_data": [
                            2.3661937713623047
                        ]
                    },
                    "name": "FT_EFF_C_systematics",
                    "type": "histosys"
                },
                {
                    "data": {
                        "hi_data": [
                            2.4139602184295654
                        ],
                        "lo_data": [
                            2.3678431510925293
                        ]
                    },
                    "name": "FT_EFF_Light_systematics",
                    "type": "histosys"
                },
                {
                    "data": {
                        "hi_data": [
                            2.3713219165802
                        ],
                        "lo_data": [
                            2.411188840866089
                        ]
                    },
                    "name": "FT_EFF_extrapolation",
                    "type": "histosys"
                },
                {
                    "data": {
                        "hi_data": [
                            2.4054346084594727
                        ],
                        "lo_data": [
                            2.411188840866089
                        ]
                    },
                    "name": "FT_EFF_extrapolation_from_charm",
                    "type": "histosys"
                },
                {
                    "data": {
                        "hi_data": [
                            2.416715383529663
                        ],
                        "lo_data": [
                            2.3872909545898438
                        ]
                    },
                    "name": "JET_JvtEfficiency",
                    "type": "histosys"
                },
                {
                    "data": {
                        "hi_data": [
                            2.3912465572357178
                        ],
                        "lo_data": [
                            2.3912465572357178
                        ]
                    },
                    "name": "MUON_EFF_BADMUON_STAT",
                    "type": "histosys"
                },
                {
                    "data": {
                        "hi_data": [
                            2.3912465572357178
                        ],
                        "lo_data": [
                            2.3912465572357178
                        ]
                    },
                    "name": "MUON_EFF_BADMUON_SYS",
                    "type": "histosys"
                },
                {
                    "data": {
                        "hi_data": [
                            2.391712188720703
                        ],
                        "lo_data": [
                            2.3907806873321533
                        ]
                    },
                    "name": "MUON_EFF_ISO_STAT",
                    "type": "histosys"
                },
                {
                    "data": {
                        "hi_data": [
                            2.3943417072296143
                        ],
                        "lo_data": [
                            2.388150930404663
                        ]
                    },
                    "name": "MUON_EFF_ISO_SYS",
                    "type": "histosys"
                },
                {
                    "data": {
                        "hi_data": [
                            2.391998291015625
                        ],
                        "lo_data": [
                            2.390493631362915
                        ]
                    },
                    "name": "MUON_EFF_RECO_STAT",
                    "type": "histosys"
                },
                {
                    "data": {
                        "hi_data": [
                            2.395477771759033
                        ],
                        "lo_data": [
                            2.387014389038086
                        ]
                    },
                    "name": "MUON_EFF_RECO_SYS",
                    "type": "histosys"
                },
                {
                    "data": {
                        "hi_data": [
                            2.3916749954223633
                        ],
                        "lo_data": [
                            2.390817880630493
                        ]
                    },
                    "name": "MUON_EFF_TTVA_STAT",
                    "type": "histosys"
                },
                {
                    "data": {
                        "hi_data": [
                            2.3913590908050537
                        ],
                        "lo_data": [
                            2.3911335468292236
                        ]
                    },
                    "name": "MUON_EFF_TTVA_SYS",
                    "type": "histosys"
                },
                {
                    "data": {
                        "hi_data": [
                            2.3912465572357178
                        ],
                        "lo_data": [
                            2.3912465572357178
                        ]
                    },
                    "name": "MUON_EFF_TrigStatUncertainty",
                    "type": "histosys"
                },
                {
                    "data": {
                        "hi_data": [
                            2.3912465572357178
                        ],
                        "lo_data": [
                            2.3912465572357178
                        ]
                    },
                    "name": "MUON_EFF_TrigSystUncertainty",
                    "type": "histosys"
                },
                {
                    "data": {
                        "hi_data": [
                            2.3912465572357178
                        ],
                        "lo_data": [
                            2.3912465572357178
                        ]
                    },
                    "name": "EG_RESOLUTION_ALL",
                    "type": "histosys"
                },
                {
                    "data": {
                        "hi_data": [
                            2.3912465572357178
                        ],
                        "lo_data": [
                            2.3912465572357178
                        ]
                    },
                    "name": "EG_SCALE_ALL",
                    "type": "histosys"
                },
                {
                    "data": {
                        "hi_data": [
                            2.3912465572357178
                        ],
                        "lo_data": [
                            2.3912465572357178
                        ]
                    },
                    "name": "JET_EtaIntercalibration_NonClosure_highE",
                    "type": "histosys"
                },
                {
                    "data": {
                        "hi_data": [
                            2.3912465572357178
                        ],
                        "lo_data": [
                            2.3912465572357178
                        ]
                    },
                    "name": "JET_EtaIntercalibration_NonClosure_negEta",
                    "type": "histosys"
                },
                {
                    "data": {
                        "hi_data": [
                            2.3912465572357178
                        ],
                        "lo_data": [
                            2.3912465572357178
                        ]
                    },
                    "name": "JET_EtaIntercalibration_NonClosure_posEta",
                    "type": "histosys"
                },
                {
                    "data": {
                        "hi_data": [
                            2.3722946643829346
                        ],
                        "lo_data": [
                            2.4830713272094727
                        ]
                    },
                    "name": "JET_Flavor_Response",
                    "type": "histosys"
                },
                {
                    "data": {
                        "hi_data": [
                            2.5189123153686523
                        ],
                        "lo_data": [
                            2.371983051300049
                        ]
                    },
                    "name": "JET_GroupedNP_1",
                    "type": "histosys"
                },
                {
                    "data": {
                        "hi_data": [
                            2.5068626403808594
                        ],
                        "lo_data": [
                            2.3704957962036133
                        ]
                    },
                    "name": "JET_GroupedNP_2",
                    "type": "histosys"
                },
                {
                    "data": {
                        "hi_data": [
                            2.391796827316284
                        ],
                        "lo_data": [
                            2.3746180534362793
                        ]
                    },
                    "name": "JET_GroupedNP_3",
                    "type": "histosys"
                },
                {
                    "data": {
                        "hi_data": [
                            2.3708412647247314
                        ],
                        "lo_data": [
                            2.3708412647247314
                        ]
                    },
                    "name": "JET_JER_DataVsMC",
                    "type": "histosys"
                },
                {
                    "data": {
                        "hi_data": [
                            2.3104259967803955
                        ],
                        "lo_data": [
                            2.3104259967803955
                        ]
                    },
                    "name": "JET_JER_EffectiveNP_1",
                    "type": "histosys"
                },
                {
                    "data": {
                        "hi_data": [
                            2.3707070350646973
                        ],
                        "lo_data": [
                            2.3707070350646973
                        ]
                    },
                    "name": "JET_JER_EffectiveNP_2",
                    "type": "histosys"
                },
                {
                    "data": {
                        "hi_data": [
                            2.414566993713379
                        ],
                        "lo_data": [
                            2.414566993713379
                        ]
                    },
                    "name": "JET_JER_EffectiveNP_3",
                    "type": "histosys"
                },
                {
                    "data": {
                        "hi_data": [
                            2.2933778762817383
                        ],
                        "lo_data": [
                            2.2933778762817383
                        ]
                    },
                    "name": "JET_JER_EffectiveNP_4",
                    "type": "histosys"
                },
                {
                    "data": {
                        "hi_data": [
                            2.413006544113159
                        ],
                        "lo_data": [
                            2.413006544113159
                        ]
                    },
                    "name": "JET_JER_EffectiveNP_5",
                    "type": "histosys"
                },
                {
                    "data": {
                        "hi_data": [
                            2.394723653793335
                        ],
                        "lo_data": [
                            2.394723653793335
                        ]
                    },
                    "name": "JET_JER_EffectiveNP_6",
                    "type": "histosys"
                },
                {
                    "data": {
                        "hi_data": [
                            2.3322153091430664
                        ],
                        "lo_data": [
                            2.3322153091430664
                        ]
                    },
                    "name": "JET_JER_EffectiveNP_7restTerm",
                    "type": "histosys"
                },
                {
                    "data": {
                        "hi_data": [
                            2.3846757411956787
                        ],
                        "lo_data": [
                            2.3846757411956787
                        ]
                    },
                    "name": "MET_SoftTrk_ResoPara",
                    "type": "histosys"
                },
                {
                    "data": {
                        "hi_data": [
                            2.3912465572357178
                        ],
                        "lo_data": [
                            2.3912465572357178
                        ]
                    },
                    "name": "MET_SoftTrk_ResoPerp",
                    "type": "histosys"
                },
                {
                    "data": {
                        "hi_data": [
                            2.3912465572357178
                        ],
                        "lo_data": [
                            2.3912465572357178
                        ]
                    },
                    "name": "MET_SoftTrk_Scale",
                    "type": "histosys"
                },
                {
                    "data": {
                        "hi_data": [
                            2.3912465572357178
                        ],
                        "lo_data": [
                            2.3912465572357178
                        ]
                    },
                    "name": "MUON_ID",
                    "type": "histosys"
                },
                {
                    "data": {
                        "hi_data": [
                            2.3912465572357178
                        ],
                        "lo_data": [
                            2.3912465572357178
                        ]
                    },
                    "name": "MUON_MS",
                    "type": "histosys"
                },
                {
                    "data": {
                        "hi_data": [
                            2.3912465572357178
                        ],
                        "lo_data": [
                            2.391253709793091
                        ]
                    },
                    "name": "MUON_SAGITTA_RESBIAS",
                    "type": "histosys"
                },
                {
                    "data": {
                        "hi_data": [
                            2.3912465572357178
                        ],
                        "lo_data": [
                            2.3912465572357178
                        ]
                    },
                    "name": "MUON_SAGITTA_RHO",
                    "type": "histosys"
                },
                {
                    "data": {
                        "hi_data": [
                            2.3912465572357178
                        ],
                        "lo_data": [
                            2.3912465572357178
                        ]
                    },
                    "name": "MUON_SCALE",
                    "type": "histosys"
                }
            ],
            "name": "sbottom_1000_850_60"
        }
    },
    {
        "op": "add",
        "path": "/channels/2/samples/0",
        "value": {
            "data": [
                1.1156052350997925
            ],
            "modifiers": [
                {
                    "data": null,
                    "name": "lumi",
                    "type": "lumi"
                },
                {
                    "data": [
                        0.1316992781243125
                    ],
                    "name": "staterror_SR_cuts",
                    "type": "staterror"
                },
                {
                    "data": {
                        "hi": 1.088,
                        "lo": 0.9369
                    },
                    "name": "SigRad",
                    "type": "normsys"
                },
                {
                    "data": null,
                    "name": "mu_SIG",
                    "type": "normfactor"
                },
                {
                    "data": {
                        "hi_data": [
                            1.1156052350997925
                        ],
                        "lo_data": [
                            1.1156052350997925
                        ]
                    },
                    "name": "EL_EFF_ChargeIDSel_TOTAL_1NPCOR_PLUS_UNCOR",
                    "type": "histosys"
                },
                {
                    "data": {
                        "hi_data": [
                            1.1156052350997925
                        ],
                        "lo_data": [
                            1.1156052350997925
                        ]
                    },
                    "name": "EL_EFF_ID_TOTAL_1NPCOR_PLUS_UNCOR",
                    "type": "histosys"
                },
                {
                    "data": {
                        "hi_data": [
                            1.1156052350997925
                        ],
                        "lo_data": [
                            1.1156052350997925
                        ]
                    },
                    "name": "EL_EFF_Iso_TOTAL_1NPCOR_PLUS_UNCOR",
                    "type": "histosys"
                },
                {
                    "data": {
                        "hi_data": [
                            1.1156052350997925
                        ],
                        "lo_data": [
                            1.1156052350997925
                        ]
                    },
                    "name": "EL_EFF_Reco_TOTAL_1NPCOR_PLUS_UNCOR",
                    "type": "histosys"
                },
                {
                    "data": {
                        "hi_data": [
                            1.1156052350997925
                        ],
                        "lo_data": [
                            1.1156052350997925
                        ]
                    },
                    "name": "EL_EFF_TriggerEff_TOTAL_1NPCOR_PLUS_UNCOR",
                    "type": "histosys"
                },
                {
                    "data": {
                        "hi_data": [
                            1.1156052350997925
                        ],
                        "lo_data": [
                            1.1156052350997925
                        ]
                    },
                    "name": "EL_EFF_Trigger_TOTAL_1NPCOR_PLUS_UNCOR",
                    "type": "histosys"
                },
                {
                    "data": {
                        "hi_data": [
                            1.0959899425506592
                        ],
                        "lo_data": [
                            1.1298402547836304
                        ]
                    },
                    "name": "FT_EFF_B_systematics",
                    "type": "histosys"
                },
                {
                    "data": {
                        "hi_data": [
                            1.11237370967865
                        ],
                        "lo_data": [
                            1.1187821626663208
                        ]
                    },
                    "name": "FT_EFF_C_systematics",
                    "type": "histosys"
                },
                {
                    "data": {
                        "hi_data": [
                            1.1327900886535645
                        ],
                        "lo_data": [
                            1.0982147455215454
                        ]
                    },
                    "name": "FT_EFF_Light_systematics",
                    "type": "histosys"
                },
                {
                    "data": {
                        "hi_data": [
                            1.0788536071777344
                        ],
                        "lo_data": [
                            1.1523784399032593
                        ]
                    },
                    "name": "FT_EFF_extrapolation",
                    "type": "histosys"
                },
                {
                    "data": {
                        "hi_data": [
                            1.1165434122085571
                        ],
                        "lo_data": [
                            1.1523784399032593
                        ]
                    },
                    "name": "FT_EFF_extrapolation_from_charm",
                    "type": "histosys"
                },
                {
                    "data": {
                        "hi_data": [
                            1.1562715768814087
                        ],
                        "lo_data": [
                            1.1307756900787354
                        ]
                    },
                    "name": "JET_JvtEfficiency",
                    "type": "histosys"
                },
                {
                    "data": {
                        "hi_data": [
                            1.1156052350997925
                        ],
                        "lo_data": [
                            1.1156052350997925
                        ]
                    },
                    "name": "MUON_EFF_BADMUON_STAT",
                    "type": "histosys"
                },
                {
                    "data": {
                        "hi_data": [
                            1.1156052350997925
                        ],
                        "lo_data": [
                            1.1156052350997925
                        ]
                    },
                    "name": "MUON_EFF_BADMUON_SYS",
                    "type": "histosys"
                },
                {
                    "data": {
                        "hi_data": [
                            1.1156052350997925
                        ],
                        "lo_data": [
                            1.1156052350997925
                        ]
                    },
                    "name": "MUON_EFF_ISO_STAT",
                    "type": "histosys"
                },
                {
                    "data": {
                        "hi_data": [
                            1.1156052350997925
                        ],
                        "lo_data": [
                            1.1156052350997925
                        ]
                    },
                    "name": "MUON_EFF_ISO_SYS",
                    "type": "histosys"
                },
                {
                    "data": {
                        "hi_data": [
                            1.1156052350997925
                        ],
                        "lo_data": [
                            1.1156052350997925
                        ]
                    },
                    "name": "MUON_EFF_RECO_STAT",
                    "type": "histosys"
                },
                {
                    "data": {
                        "hi_data": [
                            1.1156052350997925
                        ],
                        "lo_data": [
                            1.1156052350997925
                        ]
                    },
                    "name": "MUON_EFF_RECO_SYS",
                    "type": "histosys"
                },
                {
                    "data": {
                        "hi_data": [
                            1.1156052350997925
                        ],
                        "lo_data": [
                            1.1156052350997925
                        ]
                    },
                    "name": "MUON_EFF_TTVA_STAT",
                    "type": "histosys"
                },
                {
                    "data": {
                        "hi_data": [
                            1.1156052350997925
                        ],
                        "lo_data": [
                            1.1156052350997925
                        ]
                    },
                    "name": "MUON_EFF_TTVA_SYS",
                    "type": "histosys"
                },
                {
                    "data": {
                        "hi_data": [
                            1.1156052350997925
                        ],
                        "lo_data": [
                            1.1156052350997925
                        ]
                    },
                    "name": "MUON_EFF_TrigStatUncertainty",
                    "type": "histosys"
                },
                {
                    "data": {
                        "hi_data": [
                            1.1156052350997925
                        ],
                        "lo_data": [
                            1.1156052350997925
                        ]
                    },
                    "name": "MUON_EFF_TrigSystUncertainty",
                    "type": "histosys"
                },
                {
                    "data": {
                        "hi_data": [
                            1.1156052350997925
                        ],
                        "lo_data": [
                            1.1156052350997925
                        ]
                    },
                    "name": "EG_RESOLUTION_ALL",
                    "type": "histosys"
                },
                {
                    "data": {
                        "hi_data": [
                            1.1156052350997925
                        ],
                        "lo_data": [
                            1.1156052350997925
                        ]
                    },
                    "name": "EG_SCALE_ALL",
                    "type": "histosys"
                },
                {
                    "data": {
                        "hi_data": [
                            1.1156052350997925
                        ],
                        "lo_data": [
                            1.1156052350997925
                        ]
                    },
                    "name": "JET_EtaIntercalibration_NonClosure_highE",
                    "type": "histosys"
                },
                {
                    "data": {
                        "hi_data": [
                            1.1156052350997925
                        ],
                        "lo_data": [
                            1.1156052350997925
                        ]
                    },
                    "name": "JET_EtaIntercalibration_NonClosure_negEta",
                    "type": "histosys"
                },
                {
                    "data": {
                        "hi_data": [
                            1.1156047582626343
                        ],
                        "lo_data": [
                            1.1156052350997925
                        ]
                    },
                    "name": "JET_EtaIntercalibration_NonClosure_posEta",
                    "type": "histosys"
                },
                {
                    "data": {
                        "hi_data": [
                            1.184122920036316
                        ],
                        "lo_data": [
                            1.1320596933364868
                        ]
                    },
                    "name": "JET_Flavor_Response",
                    "type": "histosys"
                },
                {
                    "data": {
                        "hi_data": [
                            1.1575274467468262
                        ],
                        "lo_data": [
                            1.1376467943191528
                        ]
                    },
                    "name": "JET_GroupedNP_1",
                    "type": "histosys"
                },
                {
                    "data": {
                        "hi_data": [
                            1.1487748622894287
                        ],
                        "lo_data": [
                            1.1888024806976318
                        ]
                    },
                    "name": "JET_GroupedNP_2",
                    "type": "histosys"
                },
                {
                    "data": {
                        "hi_data": [
                            1.1244267225265503
                        ],
                        "lo_data": [
                            1.105603575706482
                        ]
                    },
                    "name": "JET_GroupedNP_3",
                    "type": "histosys"
                },
                {
                    "data": {
                        "hi_data": [
                            1.1202067136764526
                        ],
                        "lo_data": [
                            1.1202067136764526
                        ]
                    },
                    "name": "JET_JER_DataVsMC",
                    "type": "histosys"
                },
                {
                    "data": {
                        "hi_data": [
                            1.1184688806533813
                        ],
                        "lo_data": [
                            1.1184688806533813
                        ]
                    },
                    "name": "JET_JER_EffectiveNP_1",
                    "type": "histosys"
                },
                {
                    "data": {
                        "hi_data": [
                            1.1335049867630005
                        ],
                        "lo_data": [
                            1.1335049867630005
                        ]
                    },
                    "name": "JET_JER_EffectiveNP_2",
                    "type": "histosys"
                },
                {
                    "data": {
                        "hi_data": [
                            1.1242053508758545
                        ],
                        "lo_data": [
                            1.1242053508758545
                        ]
                    },
                    "name": "JET_JER_EffectiveNP_3",
                    "type": "histosys"
                },
                {
                    "data": {
                        "hi_data": [
                            1.0781391859054565
                        ],
                        "lo_data": [
                            1.0781391859054565
                        ]
                    },
                    "name": "JET_JER_EffectiveNP_4",
                    "type": "histosys"
                },
                {
                    "data": {
                        "hi_data": [
                            1.137916922569275
                        ],
                        "lo_data": [
                            1.137916922569275
                        ]
                    },
                    "name": "JET_JER_EffectiveNP_5",
                    "type": "histosys"
                },
                {
                    "data": {
                        "hi_data": [
                            1.1145681142807007
                        ],
                        "lo_data": [
                            1.1145681142807007
                        ]
                    },
                    "name": "JET_JER_EffectiveNP_6",
                    "type": "histosys"
                },
                {
                    "data": {
                        "hi_data": [
                            1.1169891357421875
                        ],
                        "lo_data": [
                            1.1169891357421875
                        ]
                    },
                    "name": "JET_JER_EffectiveNP_7restTerm",
                    "type": "histosys"
                },
                {
                    "data": {
                        "hi_data": [
                            1.1142727136611938
                        ],
                        "lo_data": [
                            1.1142727136611938
                        ]
                    },
                    "name": "MET_SoftTrk_ResoPara",
                    "type": "histosys"
                },
                {
                    "data": {
                        "hi_data": [
                            1.1244977712631226
                        ],
                        "lo_data": [
                            1.1244977712631226
                        ]
                    },
                    "name": "MET_SoftTrk_ResoPerp",
                    "type": "histosys"
                },
                {
                    "data": {
                        "hi_data": [
                            1.1058775186538696
                        ],
                        "lo_data": [
                            1.1156052350997925
                        ]
                    },
                    "name": "MET_SoftTrk_Scale",
                    "type": "histosys"
                },
                {
                    "data": {
                        "hi_data": [
                            1.1156052350997925
                        ],
                        "lo_data": [
                            1.1156052350997925
                        ]
                    },
                    "name": "MUON_ID",
                    "type": "histosys"
                },
                {
                    "data": {
                        "hi_data": [
                            1.1156052350997925
                        ],
                        "lo_data": [
                            1.1156052350997925
                        ]
                    },
                    "name": "MUON_MS",
                    "type": "histosys"
                },
                {
                    "data": {
                        "hi_data": [
                            1.1156052350997925
                        ],
                        "lo_data": [
                            1.1156052350997925
                        ]
                    },
                    "name": "MUON_SAGITTA_RESBIAS",
                    "type": "histosys"
                },
                {
                    "data": {
                        "hi_data": [
                            1.1156052350997925
                        ],
                        "lo_data": [
                            1.1156052350997925
                        ]
                    },
                    "name": "MUON_SAGITTA_RHO",
                    "type": "histosys"
                },
                {
                    "data": {
                        "hi_data": [
                            1.1156052350997925
                        ],
                        "lo_data": [
                            1.1156052350997925
                        ]
                    },
                    "name": "MUON_SCALE",
                    "type": "histosys"
                }
            ],
            "name": "sbottom_1000_850_60"
        }
    },
    {
        "op": "remove",
        "path": "/channels/1"
    }
]