[
    {
        "op": "add",
        "path": "/channels/0/samples/0",
        "value": {
            "data": [
                1.6669723987579346,
                8.026796340942383,
                9.804776191711426
            ],
            "modifiers": [
                {
                    "data": null,
                    "name": "lumi",
                    "type": "lumi"
                },
                {
                    "data": [
                        0.08011901573961631,
                        0.17798506220083576,
                        0.19986798804480777
                    ],
                    "name": "staterror_SR_meff",
                    "type": "staterror"
                },
                {
                    "data": {
                        "hi": 1.0366,
                        "lo": 0.9975
                    },
                    "name": "SigRad",
                    "type": "normsys"
                },
                {
                    "data": null,
                    "name": "mu_SIG",
                    "type": "normfactor"
                },
                {
                    "data": {
                        "hi_data": [
                            1.6669723987579346,
                            8.026796340942383,
                            9.804776191711426
                        ],
                        "lo_data": [
                            1.6669723987579346,
                            8.026796340942383,
                            9.804776191711426
                        ]
                    },
                    "name": "EL_EFF_ChargeIDSel_TOTAL_1NPCOR_PLUS_UNCOR",
                    "type": "histosys"
                },
                {
                    "data": {
                        "hi_data": [
                            1.6669723987579346,
                            8.026796340942383,
                            9.804776191711426
                        ],
                        "lo_data": [
                            1.6669723987579346,
                            8.026796340942383,
                            9.804776191711426
                        ]
                    },
                    "name": "EL_EFF_ID_TOTAL_1NPCOR_PLUS_UNCOR",
                    "type": "histosys"
                },
                {
                    "data": {
                        "hi_data": [
                            1.6669723987579346,
                            8.026796340942383,
                            9.804776191711426
                        ],
                        "lo_data": [
                            1.6669723987579346,
                            8.026796340942383,
                            9.804776191711426
                        ]
                    },
                    "name": "EL_EFF_Iso_TOTAL_1NPCOR_PLUS_UNCOR",
                    "type": "histosys"
                },
                {
                    "data": {
                        "hi_data": [
                            1.6669723987579346,
                            8.026796340942383,
                            9.804776191711426
                        ],
                        "lo_data": [
                            1.6669723987579346,
                            8.026796340942383,
                            9.804776191711426
                        ]
                    },
                    "name": "EL_EFF_Reco_TOTAL_1NPCOR_PLUS_UNCOR",
                    "type": "histosys"
                },
                {
                    "data": {
                        "hi_data": [
                            1.6669723987579346,
                            8.026796340942383,
                            9.804776191711426
                        ],
                        "lo_data": [
                            1.6669723987579346,
                            8.026796340942383,
                            9.804776191711426
                        ]
                    },
                    "name": "EL_EFF_TriggerEff_TOTAL_1NPCOR_PLUS_UNCOR",
                    "type": "histosys"
                },
                {
                    "data": {
                        "hi_data": [
                            1.6669723987579346,
                            8.026796340942383,
                            9.804776191711426
                        ],
                        "lo_data": [
                            1.6669723987579346,
                            8.026796340942383,
                            9.804776191711426
                        ]
                    },
                    "name": "EL_EFF_Trigger_TOTAL_1NPCOR_PLUS_UNCOR",
                    "type": "histosys"
                },
                {
                    "data": {
                        "hi_data": [
                            1.719507098197937,
                            8.299043655395508,
                            10.199889183044434
                        ],
                        "lo_data": [
                            1.6147379875183105,
                            7.755236625671387,
                            9.41079330444336
                        ]
                    },
                    "name": "FT_EFF_B_systematics",
                    "type": "histosys"
                },
                {
                    "data": {
                        "hi_data": [
                            1.6786532402038574,
                            8.064408302307129,
                            9.858882904052734
                        ],
                        "lo_data": [
                            1.6553221940994263,
                            7.989561557769775,
                            9.751320838928223
                        ]
                    },
                    "name": "FT_EFF_C_systematics",
                    "type": "histosys"
                },
                {
                    "data": {
                        "hi_data": [
                            1.6700174808502197,
                            8.066904067993164,
                            9.848859786987305
                        ],
                        "lo_data": [
                            1.6638619899749756,
                            7.986446380615234,
                            9.761804580688477
                        ]
                    },
                    "name": "FT_EFF_Light_systematics",
                    "type": "histosys"
                },
                {
                    "data": {
                        "hi_data": [
                            1.6670881509780884,
                            8.034479141235352,
                            9.919620513916016
                        ],
                        "lo_data": [
                            1.6668565273284912,
                            8.01911449432373,
                            9.691240310668945
                        ]
                    },
                    "name": "FT_EFF_extrapolation",
                    "type": "histosys"
                },
                {
                    "data": {
                        "hi_data": [
                            1.6728620529174805,
                            8.050531387329102,
                            9.832742691040039
                        ],
                        "lo_data": [
                            1.6668565273284912,
                            8.01911449432373,
                            9.691240310668945
                        ]
                    },
                    "name": "FT_EFF_extrapolation_from_charm",
                    "type": "histosys"
                },
                {
                    "data": {
                        "hi_data": [
                            1.6817291975021362,
                            8.061362266540527,
                            9.782326698303223
                        ],
                        "lo_data": [
                            1.6547925472259521,
                            7.959349632263184,
                            9.672459602355957
                        ]
                    },
                    "name": "JET_JvtEfficiency",
                    "type": "histosys"
                },
                {
                    "data": {
                        "hi_data": [
                            1.6669723987579346,
                            8.026796340942383,
                            9.804776191711426
                        ],
                        "lo_data": [
                            1.6669723987579346,
                            8.026796340942383,
                            9.804776191711426
                        ]
                    },
                    "name": "MUON_EFF_BADMUON_STAT",
                    "type": "histosys"
                },
                {
                    "data": {
                        "hi_data": [
                            1.6669723987579346,
                            8.026796340942383,
                            9.804776191711426
                        ],
                        "lo_data": [
                            1.6669723987579346,
                            8.026796340942383,
                            9.804776191711426
                        ]
                    },
                    "name": "MUON_EFF_BADMUON_SYS",
                    "type": "histosys"
                },
                {
                    "data": {
                        "hi_data": [
                            1.6669723987579346,
                            8.026796340942383,
                            9.804776191711426
                        ],
                        "lo_data": [
                            1.6669723987579346,
                            8.026796340942383,
                            9.804776191711426
                        ]
                    },
                    "name": "MUON_EFF_ISO_STAT",
                    "type": "histosys"
                },
                {
                    "data": {
                        "hi_data": [
                            1.6669723987579346,
                            8.026796340942383,
                            9.804776191711426
                        ],
                        "lo_data": [
                            1.6669723987579346,
                            8.026796340942383,
                            9.804776191711426
                        ]
                    },
                    "name": "MUON_EFF_ISO_SYS",
                    "type": "histosys"
                },
                {
                    "data": {
                        "hi_data": [
                            1.6669723987579346,
                            8.026796340942383,
                            9.804776191711426
                        ],
                        "lo_data": [
                            1.6669723987579346,
                            8.026796340942383,
                            9.804776191711426
                        ]
                    },
                    "name": "MUON_EFF_RECO_STAT",
                    "type": "histosys"
                },
                {
                    "data": {
                        "hi_data": [
                            1.6669723987579346,
                            8.026796340942383,
                            9.804776191711426
                        ],
                        "lo_data": [
                            1.6669723987579346,
                            8.026796340942383,
                            9.804776191711426
                        ]
                    },
                    "name": "MUON_EFF_RECO_SYS",
                    "type": "histosys"
                },
                {
                    "data": {
                        "hi_data": [
                            1.6669723987579346,
                            8.026796340942383,
                            9.804776191711426
                        ],
                        "lo_data": [
                            1.6669723987579346,
                            8.026796340942383,
                            9.804776191711426
                        ]
                    },
                    "name": "MUON_EFF_TTVA_STAT",
                    "type": "histosys"
                },
                {
                    "data": {
                        "hi_data": [
                            1.6669723987579346,
                            8.026796340942383,
                            9.804776191711426
                        ],
                        "lo_data": [
                            1.6669723987579346,
                            8.026796340942383,
                            9.804776191711426
                        ]
                    },
                    "name": "MUON_EFF_TTVA_SYS",
                    "type": "histosys"
                },
                {
                    "data": {
                        "hi_data": [
                            1.6669723987579346,
                            8.026796340942383,
                            9.804776191711426
                        ],
                        "lo_data": [
                            1.6669723987579346,
                            8.026796340942383,
                            9.804776191711426
                        ]
                    },
                    "name": "MUON_EFF_TrigStatUncertainty",
                    "type": "histosys"
                },
                {
                    "data": {
                        "hi_data": [
                            1.6669723987579346,
                            8.026796340942383,
                            9.804776191711426
                        ],
                        "lo_data": [
                            1.6669723987579346,
                            8.026796340942383,
                            9.804776191711426
                        ]
                    },
                    "name": "MUON_EFF_TrigSystUncertainty",
                    "type": "histosys"
                },
                {
                    "data": {
                        "hi_data": [
                            1.6679824590682983,
                            8.026204109191895,
                            9.802754402160645
                        ],
                        "lo_data": [
                            1.6669723987579346,
                            8.026796340942383,
                            9.804776191711426
                        ]
                    },
                    "name": "EG_RESOLUTION_ALL",
                    "type": "histosys"
                },
                {
                    "data": {
                        "hi_data": [
                            1.6669723987579346,
                            8.026796340942383,
                            9.802868843078613
                        ],
                        "lo_data": [
                            1.6669723987579346,
                            8.030038833618164,
                            9.809537887573242
                        ]
                    },
                    "name": "EG_SCALE_ALL",
                    "type": "histosys"
                },
                {
                    "data": {
                        "hi_data": [
                            1.6669723987579346,
                            8.026796340942383,
                            9.804776191711426
                        ],
                        "lo_data": [
                            1.6669723987579346,
                            8.026796340942383,
                            9.804776191711426
                        ]
                    },
                    "name": "JET_EtaIntercalibration_NonClosure_highE",
                    "type": "histosys"
                },
                {
                    "data": {
                        "hi_data": [
                            1.666979432106018,
                            8.02678108215332,
                            9.804777145385742
                        ],
                        "lo_data": [
                            1.6669650077819824,
                            8.02678108215332,
                            9.80477237701416
                        ]
                    },
                    "name": "JET_EtaIntercalibration_NonClosure_negEta",
                    "type": "histosys"
                },
                {
                    "data": {
                        "hi_data": [
                            1.6669741868972778,
                            8.026806831359863,
                            9.804776191711426
                        ],
                        "lo_data": [
                            1.6669689416885376,
                            8.026803970336914,
                            9.804777145385742
                        ]
                    },
                    "name": "JET_EtaIntercalibration_NonClosure_posEta",
                    "type": "histosys"
                },
                {
                    "data": {
                        "hi_data": [
                            1.7248878479003906,
                            7.987675666809082,
                            9.589961051940918
                        ],
                        "lo_data": [
                            1.6408733129501343,
                            8.008971214294434,
                            10.090733528137207
                        ]
                    },
                    "name": "JET_Flavor_Response",
                    "type": "histosys"
                },
                {
                    "data": {
                        "hi_data": [
                            1.634590983390808,
                            8.051212310791016,
                            10.23474407196045
                        ],
                        "lo_data": [
                            1.7253913879394531,
                            7.9915852546691895,
                            9.461321830749512
                        ]
                    },
                    "name": "JET_GroupedNP_1",
                    "type": "histosys"
                },
                {
                    "data": {
                        "hi_data": [
                            1.6330865621566772,
                            8.085463523864746,
                            10.219176292419434
                        ],
                        "lo_data": [
                            1.7359418869018555,
                            7.960680961608887,
                            9.49185562133789
                        ]
                    },
                    "name": "JET_GroupedNP_2",
                    "type": "histosys"
                },
                {
                    "data": {
                        "hi_data": [
                            1.650146722793579,
                            7.98240327835083,
                            9.915605545043945
                        ],
                        "lo_data": [
                            1.6717860698699951,
                            8.051609992980957,
                            9.70261001586914
                        ]
                    },
                    "name": "JET_GroupedNP_3",
                    "type": "histosys"
                },
                {
                    "data": {
                        "hi_data": [
                            1.6651571989059448,
                            8.024398803710938,
                            9.814437866210938
                        ],
                        "lo_data": [
                            1.6651571989059448,
                            8.024398803710938,
                            9.814437866210938
                        ]
                    },
                    "name": "JET_JER_DataVsMC",
                    "type": "histosys"
                },
                {
                    "data": {
                        "hi_data": [
                            1.6514322757720947,
                            7.9681878089904785,
                            9.830880165100098
                        ],
                        "lo_data": [
                            1.6514322757720947,
                            7.9681878089904785,
                            9.830880165100098
                        ]
                    },
                    "name": "JET_JER_EffectiveNP_1",
                    "type": "histosys"
                },
                {
                    "data": {
                        "hi_data": [
                            1.6287106275558472,
                            8.003199577331543,
                            9.810981750488281
                        ],
                        "lo_data": [
                            1.6287106275558472,
                            8.003199577331543,
                            9.810981750488281
                        ]
                    },
                    "name": "JET_JER_EffectiveNP_2",
                    "type": "histosys"
                },
                {
                    "data": {
                        "hi_data": [
                            1.646143913269043,
                            8.04479694366455,
                            9.782559394836426
                        ],
                        "lo_data": [
                            1.646143913269043,
                            8.04479694366455,
                            9.782559394836426
                        ]
                    },
                    "name": "JET_JER_EffectiveNP_3",
                    "type": "histosys"
                },
                {
                    "data": {
                        "hi_data": [
                            1.6646605730056763,
                            8.005514144897461,
                            9.833847045898438
                        ],
                        "lo_data": [
                            1.6646605730056763,
                            8.005514144897461,
                            9.833847045898438
                        ]
                    },
                    "name": "JET_JER_EffectiveNP_4",
                    "type": "histosys"
                },
                {
                    "data": {
                        "hi_data": [
                            1.6723207235336304,
                            8.012868881225586,
                            9.824117660522461
                        ],
                        "lo_data": [
                            1.6723207235336304,
                            8.012868881225586,
                            9.824117660522461
                        ]
                    },
                    "name": "JET_JER_EffectiveNP_5",
                    "type": "histosys"
                },
                {
                    "data": {
                        "hi_data": [
                            1.682782769203186,
                            8.013943672180176,
                            9.801848411560059
                        ],
                        "lo_data": [
                            1.682782769203186,
                            8.013943672180176,
                            9.801848411560059
                        ]
                    },
                    "name": "JET_JER_EffectiveNP_6",
                    "type": "histosys"
                },
                {
                    "data": {
                        "hi_data": [
                            1.6528830528259277,
                            8.011927604675293,
                            9.828812599182129
                        ],
                        "lo_data": [
                            1.6528830528259277,
                            8.011927604675293,
                            9.828812599182129
                        ]
                    },
                    "name": "JET_JER_EffectiveNP_7restTerm",
                    "type": "histosys"
                },
                {
                    "data": {
                        "hi_data": [
                            1.65776526927948,
                            8.044296264648438,
                            9.777759552001953
                        ],
                        "lo_data": [
                            1.65776526927948,
                            8.044296264648438,
                            9.777759552001953
                        ]
                    },
                    "name": "MET_SoftTrk_ResoPara",
                    "type": "histosys"
                },
                {
                    "data": {
                        "hi_data": [
                            1.6687757968902588,
                            8.02074909210205,
                            9.798726081848145
                        ],
                        "lo_data": [
                            1.6687757968902588,
                            8.02074909210205,
                            9.798726081848145
                        ]
                    },
                    "name": "MET_SoftTrk_ResoPerp",
                    "type": "histosys"
                },
                {
                    "data": {
                        "hi_data": [
                            1.6560767889022827,
                            8.019635200500488,
                            9.80685806274414
                        ],
                        "lo_data": [
                            1.668676733970642,
                            8.037296295166016,
                            9.80704402923584
                        ]
                    },
                    "name": "MET_SoftTrk_Scale",
                    "type": "histosys"
                },
                {
                    "data": {
                        "hi_data": [
                            1.6669723987579346,
                            8.026796340942383,
                            9.804776191711426
                        ],
                        "lo_data": [
                            1.6669723987579346,
                            8.029420852661133,
                            9.804776191711426
                        ]
                    },
                    "name": "MUON_ID",
                    "type": "histosys"
                },
                {
                    "data": {
                        "hi_data": [
                            1.6669723987579346,
                            8.026796340942383,
                            9.804776191711426
                        ],
                        "lo_data": [
                            1.6669723987579346,
                            8.029420852661133,
                            9.802604675292969
                        ]
                    },
                    "name": "MUON_MS",
                    "type": "histosys"
                },
                {
                    "data": {
                        "hi_data": [
                            1.6633756160736084,
                            8.03006362915039,
                            9.807948112487793
                        ],
                        "lo_data": [
                            1.6669723987579346,
                            8.029420852661133,
                            9.810523986816406
                        ]
                    },
                    "name": "MUON_SAGITTA_RESBIAS",
                    "type": "histosys"
                },
                {
                    "data": {
                        "hi_data": [
                            1.6669723987579346,
                            8.026796340942383,
                            9.804776191711426
                        ],
                        "lo_data": [
                            1.6669723987579346,
                            8.026796340942383,
                            9.804776191711426
                        ]
                    },
                    "name": "MUON_SAGITTA_RHO",
                    "type": "histosys"
                },
                {
                    "data": {
                        "hi_data": [
                            1.6669723987579346,
                            8.026796340942383,
                            9.804776191711426
                        ],
                        "lo_data": [
                            1.6669723987579346,
                            8.029420852661133,
                            9.804776191711426
                        ]
                    },
                    "name": "MUON_SCALE",
                    "type": "histosys"
                }
            ],
            "name": "sbottom_1200_950_60"
        }
    },
    {
        "op": "add",
        "path": "/channels/2/samples/0",
        "value": {
            "data": [
                1.6777491569519043,
                2.667893648147583,
                1.7367912530899048
            ],
            "modifiers": [
                {
                    "data": null,
                    "name": "lumi",
                    "type": "lumi"
                },
                {
                    "data": [
                        0.15515577100926597,
                        0.19493652000398115,
                        0.16342061569604407
                    ],
                    "name": "staterror_CRtt_meff",
                    "type": "staterror"
                },
                {
                    "data": {
                        "hi": 1.0366,
                        "lo": 0.9975
                    },
                    "name": "SigRad",
                    "type": "normsys"
                },
                {
                    "data": null,
                    "name": "mu_SIG",
                    "type": "normfactor"
                },
                {
                    "data": {
                        "hi_data": [
                            1.6777491569519043,
                            2.667893648147583,
                            1.7367912530899048
                        ],
                        "lo_data": [
                            1.6777491569519043,
                            2.667893648147583,
                            1.7367912530899048
                        ]
                    },
                    "name": "EL_EFF_ChargeIDSel_TOTAL_1NPCOR_PLUS_UNCOR",
                    "type": "histosys"
                },
                {
                    "data": {
                        "hi_data": [
                            1.6865216493606567,
                            2.680504083633423,
                            1.7451614141464233
                        ],
                        "lo_data": [
                            1.6689759492874146,
                            2.655285596847534,
                            1.7284213304519653
                        ]
                    },
                    "name": "EL_EFF_ID_TOTAL_1NPCOR_PLUS_UNCOR",
                    "type": "histosys"
                },
                {
                    "data": {
                        "hi_data": [
                            1.6799514293670654,
                            2.670741558074951,
                            1.7385010719299316
                        ],
                        "lo_data": [
                            1.6755459308624268,
                            2.6650454998016357,
                            1.7350817918777466
                        ]
                    },
                    "name": "EL_EFF_Iso_TOTAL_1NPCOR_PLUS_UNCOR",
                    "type": "histosys"
                },
                {
                    "data": {
                        "hi_data": [
                            1.679012656211853,
                            2.6697869300842285,
                            1.7381540536880493
                        ],
                        "lo_data": [
                            1.6764850616455078,
                            2.6660003662109375,
                            1.7354282140731812
                        ]
                    },
                    "name": "EL_EFF_Reco_TOTAL_1NPCOR_PLUS_UNCOR",
                    "type": "histosys"
                },
                {
                    "data": {
                        "hi_data": [
                            1.6777491569519043,
                            2.667893648147583,
                            1.7367912530899048
                        ],
                        "lo_data": [
                            1.6777491569519043,
                            2.667893648147583,
                            1.7367912530899048
                        ]
                    },
                    "name": "EL_EFF_TriggerEff_TOTAL_1NPCOR_PLUS_UNCOR",
                    "type": "histosys"
                },
                {
                    "data": {
                        "hi_data": [
                            1.6777491569519043,
                            2.667893648147583,
                            1.7367912530899048
                        ],
                        "lo_data": [
                            1.6777491569519043,
                            2.667893648147583,
                            1.7367912530899048
                        ]
                    },
                    "name": "EL_EFF_Trigger_TOTAL_1NPCOR_PLUS_UNCOR",
                    "type": "histosys"
                },
                {
                    "data": {
                        "hi_data": [
                            1.760075569152832,
                            2.803527355194092,
                            1.8217782974243164
                        ],
                        "lo_data": [
                            1.5983164310455322,
                            2.536799907684326,
                            1.654165506362915
                        ]
                    },
                    "name": "FT_EFF_B_systematics",
                    "type": "histosys"
                },
                {
                    "data": {
                        "hi_data": [
                            1.7041711807250977,
                            2.7093324661254883,
                            1.756617546081543
                        ],
                        "lo_data": [
                            1.6522762775421143,
                            2.626354932785034,
                            1.716567039489746
                        ]
                    },
                    "name": "FT_EFF_C_systematics",
                    "type": "histosys"
                },
                {
                    "data": {
                        "hi_data": [
                            1.6912543773651123,
                            2.6984009742736816,
                            1.779374599456787
                        ],
                        "lo_data": [
                            1.6639878749847412,
                            2.637852668762207,
                            1.6933481693267822
                        ]
                    },
                    "name": "FT_EFF_Light_systematics",
                    "type": "histosys"
                },
                {
                    "data": {
                        "hi_data": [
                            1.6780195236206055,
                            2.671300172805786,
                            1.7596262693405151
                        ],
                        "lo_data": [
                            1.6774784326553345,
                            2.6644859313964844,
                            1.713786244392395
                        ]
                    },
                    "name": "FT_EFF_extrapolation",
                    "type": "histosys"
                },
                {
                    "data": {
                        "hi_data": [
                            1.6925220489501953,
                            2.689995050430298,
                            1.742823600769043
                        ],
                        "lo_data": [
                            1.6774784326553345,
                            2.6644859313964844,
                            1.713786244392395
                        ]
                    },
                    "name": "FT_EFF_extrapolation_from_charm",
                    "type": "histosys"
                },
                {
                    "data": {
                        "hi_data": [
                            1.6845756769180298,
                            2.6613614559173584,
                            1.7499477863311768
                        ],
                        "lo_data": [
                            1.6536465883255005,
                            2.621344566345215,
                            1.7296676635742188
                        ]
                    },
                    "name": "JET_JvtEfficiency",
                    "type": "histosys"
                },
                {
                    "data": {
                        "hi_data": [
                            1.6777491569519043,
                            2.667893648147583,
                            1.7367912530899048
                        ],
                        "lo_data": [
                            1.6777491569519043,
                            2.667893648147583,
                            1.7367912530899048
                        ]
                    },
                    "name": "MUON_EFF_BADMUON_STAT",
                    "type": "histosys"
                },
                {
                    "data": {
                        "hi_data": [
                            1.6777491569519043,
                            2.667893648147583,
                            1.7367912530899048
                        ],
                        "lo_data": [
                            1.6777491569519043,
                            2.667893648147583,
                            1.7367912530899048
                        ]
                    },
                    "name": "MUON_EFF_BADMUON_SYS",
                    "type": "histosys"
                },
                {
                    "data": {
                        "hi_data": [
                            1.6780211925506592,
                            2.6685121059417725,
                            1.7371840476989746
                        ],
                        "lo_data": [
                            1.6774765253067017,
                            2.6672723293304443,
                            1.7364000082015991
                        ]
                    },
                    "name": "MUON_EFF_ISO_STAT",
                    "type": "histosys"
                },
                {
                    "data": {
                        "hi_data": [
                            1.679680347442627,
                            2.6712582111358643,
                            1.7389912605285645
                        ],
                        "lo_data": [
                            1.6758174896240234,
                            2.6645262241363525,
                            1.7345924377441406
                        ]
                    },
                    "name": "MUON_EFF_ISO_SYS",
                    "type": "histosys"
                },
                {
                    "data": {
                        "hi_data": [
                            1.6784402132034302,
                            2.668926477432251,
                            1.7373950481414795
                        ],
                        "lo_data": [
                            1.6770581007003784,
                            2.6668574810028076,
                            1.7361886501312256
                        ]
                    },
                    "name": "MUON_EFF_RECO_STAT",
                    "type": "histosys"
                },
                {
                    "data": {
                        "hi_data": [
                            1.681727647781372,
                            2.6732399463653564,
                            1.7400867938995361
                        ],
                        "lo_data": [
                            1.6737701892852783,
                            2.6625444889068604,
                            1.7334964275360107
                        ]
                    },
                    "name": "MUON_EFF_RECO_SYS",
                    "type": "histosys"
                },
                {
                    "data": {
                        "hi_data": [
                            1.6780123710632324,
                            2.668391466140747,
                            1.737130045890808
                        ],
                        "lo_data": [
                            1.6774860620498657,
                            2.667391538619995,
                            1.7364531755447388
                        ]
                    },
                    "name": "MUON_EFF_TTVA_STAT",
                    "type": "histosys"
                },
                {
                    "data": {
                        "hi_data": [
                            1.6778509616851807,
                            2.6680779457092285,
                            1.7369035482406616
                        ],
                        "lo_data": [
                            1.6776471138000488,
                            2.6677064895629883,
                            1.7366797924041748
                        ]
                    },
                    "name": "MUON_EFF_TTVA_SYS",
                    "type": "histosys"
                },
                {
                    "data": {
                        "hi_data": [
                            1.6777491569519043,
                            2.667893648147583,
                            1.7367912530899048
                        ],
                        "lo_data": [
                            1.6777491569519043,
                            2.667893648147583,
                            1.7367912530899048
                        ]
                    },
                    "name": "MUON_EFF_TrigStatUncertainty",
                    "type": "histosys"
                },
                {
                    "data": {
                        "hi_data": [
                            1.6777491569519043,
                            2.667893648147583,
                            1.7367912530899048
                        ],
                        "lo_data": [
                            1.6777491569519043,
                            2.667893648147583,
                            1.7367912530899048
                        ]
                    },
                    "name": "MUON_EFF_TrigSystUncertainty",
                    "type": "histosys"
                },
                {
                    "data": {
                        "hi_data": [
                            1.6777491569519043,
                            2.667955160140991,
                            1.7314000129699707
                        ],
                        "lo_data": [
                            1.6777362823486328,
                            2.6679270267486572,
                            1.7367912530899048
                        ]
                    },
                    "name": "EG_RESOLUTION_ALL",
                    "type": "histosys"
                },
                {
                    "data": {
                        "hi_data": [
                            1.6777491569519043,
                            2.667893648147583,
                            1.7367912530899048
                        ],
                        "lo_data": [
                            1.6777362823486328,
                            2.6681835651397705,
                            1.7381736040115356
                        ]
                    },
                    "name": "EG_SCALE_ALL",
                    "type": "histosys"
                },
                {
                    "data": {
                        "hi_data": [
                            1.6777491569519043,
                            2.667893648147583,
                            1.7367912530899048
                        ],
                        "lo_data": [
                            1.6777491569519043,
                            2.667893648147583,
                            1.7367912530899048
                        ]
                    },
                    "name": "JET_EtaIntercalibration_NonClosure_highE",
                    "type": "histosys"
                },
                {
                    "data": {
                        "hi_data": [
                            1.6952311992645264,
                            2.667896270751953,
                            1.7367916107177734
                        ],
                        "lo_data": [
                            1.6777491569519043,
                            2.667893171310425,
                            1.7367918491363525
                        ]
                    },
                    "name": "JET_EtaIntercalibration_NonClosure_negEta",
                    "type": "histosys"
                },
                {
                    "data": {
                        "hi_data": [
                            1.6777491569519043,
                            2.667891025543213,
                            1.7367911338806152
                        ],
                        "lo_data": [
                            1.6777491569519043,
                            2.667893171310425,
                            1.7367863655090332
                        ]
                    },
                    "name": "JET_EtaIntercalibration_NonClosure_posEta",
                    "type": "histosys"
                },
                {
                    "data": {
                        "hi_data": [
                            1.7541801929473877,
                            2.598386764526367,
                            1.6625595092773438
                        ],
                        "lo_data": [
                            1.7203508615493774,
                            2.743662118911743,
                            1.7743945121765137
                        ]
                    },
                    "name": "JET_Flavor_Response",
                    "type": "histosys"
                },
                {
                    "data": {
                        "hi_data": [
                            1.7273129224777222,
                            2.7826852798461914,
                            1.814371109008789
                        ],
                        "lo_data": [
                            1.7306981086730957,
                            2.589783191680908,
                            1.647385835647583
                        ]
                    },
                    "name": "JET_GroupedNP_1",
                    "type": "histosys"
                },
                {
                    "data": {
                        "hi_data": [
                            1.718656063079834,
                            2.7965707778930664,
                            1.8095152378082275
                        ],
                        "lo_data": [
                            1.7466471195220947,
                            2.5936994552612305,
                            1.60239839553833
                        ]
                    },
                    "name": "JET_GroupedNP_2",
                    "type": "histosys"
                },
                {
                    "data": {
                        "hi_data": [
                            1.7165021896362305,
                            2.6844871044158936,
                            1.7416481971740723
                        ],
                        "lo_data": [
                            1.7181921005249023,
                            2.6870758533477783,
                            1.6967442035675049
                        ]
                    },
                    "name": "JET_GroupedNP_3",
                    "type": "histosys"
                },
                {
                    "data": {
                        "hi_data": [
                            1.6521880626678467,
                            2.6454362869262695,
                            1.7298545837402344
                        ],
                        "lo_data": [
                            1.6521880626678467,
                            2.6454362869262695,
                            1.7298545837402344
                        ]
                    },
                    "name": "JET_JER_DataVsMC",
                    "type": "histosys"
                },
                {
                    "data": {
                        "hi_data": [
                            1.6933335065841675,
                            2.641309976577759,
                            1.7778801918029785
                        ],
                        "lo_data": [
                            1.6933335065841675,
                            2.641309976577759,
                            1.7778801918029785
                        ]
                    },
                    "name": "JET_JER_EffectiveNP_1",
                    "type": "histosys"
                },
                {
                    "data": {
                        "hi_data": [
                            1.6860542297363281,
                            2.6572608947753906,
                            1.7539787292480469
                        ],
                        "lo_data": [
                            1.6860542297363281,
                            2.6572608947753906,
                            1.7539787292480469
                        ]
                    },
                    "name": "JET_JER_EffectiveNP_2",
                    "type": "histosys"
                },
                {
                    "data": {
                        "hi_data": [
                            1.6984708309173584,
                            2.6643214225769043,
                            1.7351685762405396
                        ],
                        "lo_data": [
                            1.6984708309173584,
                            2.6643214225769043,
                            1.7351685762405396
                        ]
                    },
                    "name": "JET_JER_EffectiveNP_3",
                    "type": "histosys"
                },
                {
                    "data": {
                        "hi_data": [
                            1.717374563217163,
                            2.6677067279815674,
                            1.7670546770095825
                        ],
                        "lo_data": [
                            1.717374563217163,
                            2.6677067279815674,
                            1.7670546770095825
                        ]
                    },
                    "name": "JET_JER_EffectiveNP_4",
                    "type": "histosys"
                },
                {
                    "data": {
                        "hi_data": [
                            1.7084492444992065,
                            2.7190370559692383,
                            1.7486047744750977
                        ],
                        "lo_data": [
                            1.7084492444992065,
                            2.7190370559692383,
                            1.7486047744750977
                        ]
                    },
                    "name": "JET_JER_EffectiveNP_5",
                    "type": "histosys"
                },
                {
                    "data": {
                        "hi_data": [
                            1.7622476816177368,
                            2.689946413040161,
                            1.729334831237793
                        ],
                        "lo_data": [
                            1.7622476816177368,
                            2.689946413040161,
                            1.729334831237793
                        ]
                    },
                    "name": "JET_JER_EffectiveNP_6",
                    "type": "histosys"
                },
                {
                    "data": {
                        "hi_data": [
                            1.7082488536834717,
                            2.6804182529449463,
                            1.7672436237335205
                        ],
                        "lo_data": [
                            1.7082488536834717,
                            2.6804182529449463,
                            1.7672436237335205
                        ]
                    },
                    "name": "JET_JER_EffectiveNP_7restTerm",
                    "type": "histosys"
                },
                {
                    "data": {
                        "hi_data": [
                            1.667665719985962,
                            2.690962076187134,
                            1.713722825050354
                        ],
                        "lo_data": [
                            1.667665719985962,
                            2.690962076187134,
                            1.713722825050354
                        ]
                    },
                    "name": "MET_SoftTrk_ResoPara",
                    "type": "histosys"
                },
                {
                    "data": {
                        "hi_data": [
                            1.7144043445587158,
                            2.648416757583618,
                            1.7367912530899048
                        ],
                        "lo_data": [
                            1.7144043445587158,
                            2.648416757583618,
                            1.7367912530899048
                        ]
                    },
                    "name": "MET_SoftTrk_ResoPerp",
                    "type": "histosys"
                },
                {
                    "data": {
                        "hi_data": [
                            1.6998374462127686,
                            2.686617136001587,
                            1.7180675268173218
                        ],
                        "lo_data": [
                            1.6952311992645264,
                            2.667893648147583,
                            1.7367912530899048
                        ]
                    },
                    "name": "MET_SoftTrk_Scale",
                    "type": "histosys"
                },
                {
                    "data": {
                        "hi_data": [
                            1.6777575016021729,
                            2.686561346054077,
                            1.7128957509994507
                        ],
                        "lo_data": [
                            1.6777491569519043,
                            2.6679012775421143,
                            1.7367969751358032
                        ]
                    },
                    "name": "MUON_ID",
                    "type": "histosys"
                },
                {
                    "data": {
                        "hi_data": [
                            1.677748203277588,
                            2.66789174079895,
                            1.7367912530899048
                        ],
                        "lo_data": [
                            1.6777443885803223,
                            2.6866281032562256,
                            1.7180616855621338
                        ]
                    },
                    "name": "MUON_MS",
                    "type": "histosys"
                },
                {
                    "data": {
                        "hi_data": [
                            1.7095980644226074,
                            2.6923086643218994,
                            1.6787071228027344
                        ],
                        "lo_data": [
                            1.7147080898284912,
                            2.6719038486480713,
                            1.7019612789154053
                        ]
                    },
                    "name": "MUON_SAGITTA_RESBIAS",
                    "type": "histosys"
                },
                {
                    "data": {
                        "hi_data": [
                            1.6777491569519043,
                            2.667893648147583,
                            1.7367912530899048
                        ],
                        "lo_data": [
                            1.6777491569519043,
                            2.667893648147583,
                            1.7367912530899048
                        ]
                    },
                    "name": "MUON_SAGITTA_RHO",
                    "type": "histosys"
                },
                {
                    "data": {
                        "hi_data": [
                            1.6777491569519043,
                            2.686617136001587,
                            1.718060851097107
                        ],
                        "lo_data": [
                            1.6777491569519043,
                            2.667893648147583,
                            1.736791968345642
                        ]
                    },
                    "name": "MUON_SCALE",
                    "type": "histosys"
                }
            ],
            "name": "sbottom_1200_950_60"
        }
    },
    {
        "op": "remove",
        "path": "/channels/1"
    }
]